hydrotools/nwm_client_new/AzureFileCatalog.py
hydrotools/nwm_client_new/FileDownloader.py
hydrotools/nwm_client_new/GCPFileCatalog.py
hydrotools/nwm_client_new/HTTPFileCatalog.py
hydrotools/nwm_client_new/NWMClient.py
hydrotools/nwm_client_new/NWMClientDefaults.py
hydrotools/nwm_client_new/NWMFileCatalog.py
hydrotools/nwm_client_new/NWMFileClient.py
hydrotools/nwm_client_new/NWMFileProcessor.py
hydrotools/nwm_client_new/ParquetStore.py
hydrotools/nwm_client_new/UnitHandler.py
hydrotools/nwm_client_new/__init__.py
hydrotools/nwm_client_new/_version.py
hydrotools.nwm_client_new-8.0.0.dist-info/LICENSE
hydrotools.nwm_client_new-8.0.0.dist-info/METADATA
hydrotools.nwm_client_new-8.0.0.dist-info/WHEEL
hydrotools.nwm_client_new-8.0.0.dist-info/top_level.txt
hydrotools.nwm_client_new-8.0.0.dist-info/RECORD
