Metadata-Version: 2.1
Name: hydrotools.nwm_client_new
Version: 8.0.0
Summary: Retrieve National Water Model data from various sources.
Author-email: "Jason A. Regina" <jason.regina@noaa.gov>
License: “Software code created by U.S. Government employees is not subject to copyright
Project-URL: Homepage, https://github.com/NOAA-OWP/hydrotools
Project-URL: Documentation, https://noaa-owp.github.io/hydrotools/hydrotools.nwm_client_new.html
Project-URL: Repository, https://github.com/NOAA-OWP/hydrotools/tree/main/python/nwm_client_new
Project-URL: Bug Tracker, https://github.com/NOAA-OWP/hydrotools/issues
Classifier: Development Status :: 5 - Production/Stable
Classifier: Intended Audience :: Education
Classifier: Intended Audience :: Science/Research
Classifier: License :: Free To Use But Restricted
Classifier: Programming Language :: Python :: 3.8
Classifier: Programming Language :: Python :: 3.9
Classifier: Programming Language :: Python :: 3.10
Classifier: Programming Language :: Python :: 3.11
Classifier: Topic :: Scientific/Engineering :: Hydrology
Classifier: Operating System :: OS Independent
Requires-Python: >=3.8
License-File: LICENSE
Requires-Dist: numpy<2,>=1.20.0; python_version < "3.10"
Requires-Dist: numpy>=1.20.0
Requires-Dist: pandas
Requires-Dist: xarray
Requires-Dist: beautifulsoup4
Requires-Dist: google-cloud-storage
Requires-Dist: dask
Requires-Dist: pyarrow
Requires-Dist: aiohttp
Requires-Dist: aiofiles
Requires-Dist: netcdf4
Requires-Dist: tables
Requires-Dist: pint
Requires-Dist: azure-storage-blob
Requires-Dist: planetary-computer
Requires-Dist: adlfs
Requires-Dist: hydrotools._restclient
Requires-Dist: dask[dataframe]
Provides-Extra: develop
Requires-Dist: pytest; extra == "develop"
